securityscorecard_api/__init__.py
securityscorecard_api/_defaults.py
securityscorecard_api/client.py
securityscorecard_api/compliance.py
securityscorecard_api/events.py
securityscorecard_api/scores.py
securityscorecard_api/version.py
securityscorecard_api/version2.py
securityscorecard_api/utils/__init__.py
securityscorecard_api/utils/utils.py
securityscorecard_api-0.10.8.dist-info/METADATA
securityscorecard_api-0.10.8.dist-info/WHEEL
securityscorecard_api-0.10.8.dist-info/top_level.txt
securityscorecard_api-0.10.8.dist-info/RECORD
